getpublicipv4/README.MD
getpublicipv4/__init__.py
getpublicipv4/requirements.txt
getpublicipv4/thirdparty.json
getpublicipv4-0.12.dist-info/LICENSE.rst
getpublicipv4-0.12.dist-info/METADATA
getpublicipv4-0.12.dist-info/WHEEL
getpublicipv4-0.12.dist-info/top_level.txt
getpublicipv4-0.12.dist-info/RECORD
