Metadata-Version: 2.1
Name: getpublicipv4
Version: 0.12
Summary: script to get the public IP (v4) of a PC
Home-page: https://github.com/hansalemaos/getpublicipv4
Author: Johannes Fischer
Author-email: aulasparticularesdealemaosp@gmail.com
License: MIT
Keywords: requests,ip,v4
Classifier: Development Status :: 4 - Beta
Classifier: Programming Language :: Python :: 3 :: Only
Classifier: Programming Language :: Python :: 3.10
Classifier: Topic :: Software Development :: Libraries :: Python Modules
Classifier: Topic :: Utilities
License-File: LICENSE.rst
Requires-Dist: requests
